china_bean_importers/__init__.py
china_bean_importers/common.py
china_bean_importers/dedup.py
china_bean_importers/importer.py
china_bean_importers/alipay_mobile/__init__.py
china_bean_importers/alipay_web/__init__.py
china_bean_importers/boc_credit_card/__init__.py
china_bean_importers/boc_debit_card/__init__.py
china_bean_importers/ccb_debit_card/__init__.py
china_bean_importers/cmb_debit_card/__init__.py
china_bean_importers/cmbc_credit_card/__init__.py
china_bean_importers/cmbc_debit_card/__init__.py
china_bean_importers/hsbc_hk/__init__.py
china_bean_importers/icbc_debit_card/__init__.py
china_bean_importers/thu_ecard/__init__.py
china_bean_importers/thu_ecard/decode.js
china_bean_importers/thu_ecard_old/__init__.py
china_bean_importers/wechat/__init__.py
china_bean_importers-0.0.4.dist-info/licenses/LICENSE
china_bean_importers-0.0.4.dist-info/WHEEL
china_bean_importers-0.0.4.dist-info/METADATA
china_bean_importers-0.0.4.dist-info/RECORD
