Metadata-Version: 2.4
Name: china_bean_importers
Version: 0.0.4
Summary: Beancount importers for Chinese users
Requires-Python: >=3.9,<4
License-Expression: MIT
License-File: LICENSE
Requires-Dist: pymupdf
Requires-Dist: beancount < 3
Requires-Dist: BeautifulSoup4
Project-URL: repository, https://github.com/jiegec/china_bean_importers
